masedb/__init__.py
masedb/async_client.py
masedb/client.py
masedb/exceptions.py
masedb-0.2.6.dist-info/licenses/LICENSE
masedb-0.2.6.dist-info/METADATA
masedb-0.2.6.dist-info/WHEEL
masedb-0.2.6.dist-info/top_level.txt
masedb-0.2.6.dist-info/RECORD
